bootstrap_customizer/__init__.py
bootstrap_customizer/admin.py
bootstrap_customizer/constants.py
bootstrap_customizer/middleware.py
bootstrap_customizer/models.py
bootstrap_customizer/urls.py
bootstrap_customizer/utils.py
bootstrap_customizer/views.py
bootstrap_customizer/migrations/0001_initial.py
bootstrap_customizer/migrations/0002_auto_20180909_0409.py
bootstrap_customizer/migrations/__init__.py
bootstrap_customizer/static/bootstrap/LICENSE
bootstrap_customizer/static/bootstrap/dist/css/bootstrap-grid.css
bootstrap_customizer/static/bootstrap/dist/css/bootstrap-grid.css.map
bootstrap_customizer/static/bootstrap/dist/css/bootstrap-grid.min.css
bootstrap_customizer/static/bootstrap/dist/css/bootstrap-grid.min.css.map
bootstrap_customizer/static/bootstrap/dist/css/bootstrap-reboot.css
bootstrap_customizer/static/bootstrap/dist/css/bootstrap-reboot.css.map
bootstrap_customizer/static/bootstrap/dist/css/bootstrap-reboot.min.css
bootstrap_customizer/static/bootstrap/dist/css/bootstrap-reboot.min.css.map
bootstrap_customizer/static/bootstrap/dist/css/bootstrap.css
bootstrap_customizer/static/bootstrap/dist/css/bootstrap.css.map
bootstrap_customizer/static/bootstrap/dist/css/bootstrap.min.css
bootstrap_customizer/static/bootstrap/dist/css/bootstrap.min.css.map
bootstrap_customizer/static/bootstrap/dist/js/bootstrap.bundle.js
bootstrap_customizer/static/bootstrap/dist/js/bootstrap.bundle.js.map
bootstrap_customizer/static/bootstrap/dist/js/bootstrap.bundle.min.js
bootstrap_customizer/static/bootstrap/dist/js/bootstrap.bundle.min.js.map
bootstrap_customizer/static/bootstrap/dist/js/bootstrap.js
bootstrap_customizer/static/bootstrap/dist/js/bootstrap.js.map
bootstrap_customizer/static/bootstrap/dist/js/bootstrap.min.js
bootstrap_customizer/static/bootstrap/dist/js/bootstrap.min.js.map
bootstrap_customizer/static/bootstrap/scss/_alert.scss
bootstrap_customizer/static/bootstrap/scss/_badge.scss
bootstrap_customizer/static/bootstrap/scss/_breadcrumb.scss
django_bootstrap_customizer-0.2.0.dist-info/AUTHORS.md
django_bootstrap_customizer-0.2.0.dist-info/LICENSE
django_bootstrap_customizer-0.2.0.dist-info/METADATA
django_bootstrap_customizer-0.2.0.dist-info/WHEEL
django_bootstrap_customizer-0.2.0.dist-info/top_level.txt
django_bootstrap_customizer-0.2.0.dist-info/RECORD
