Metadata-Version: 2.1
Name: django-bootstrap-customizer
Version: 0.2.0
Summary: Build customized Bootstrap CSS using the Django admin
Home-page: https://github.com/johnfraney/django-bootstrap-customizer
Author: John Franey
Author-email: johnfraney@gmail.com
License: MIT
Keywords: django-bootstrap-customizer
Platform: UNKNOWN
Classifier: Development Status :: 4 - Beta
Classifier: Framework :: Django :: 1.11
Classifier: Framework :: Django :: 2.1
Classifier: Framework :: Django :: 2.2
Classifier: Intended Audience :: Developers
Classifier: License :: OSI Approved :: BSD License
Classifier: Natural Language :: English
Classifier: Programming Language :: Python :: 2
Classifier: Programming Language :: Python :: 2.7
Classifier: Programming Language :: Python :: 3
Classifier: Programming Language :: Python :: 3.4
Classifier: Programming Language :: Python :: 3.5
Classifier: Programming Language :: Python :: 3.6
Classifier: Programming Language :: Python :: 3.7
Classifier: Programming Language :: Python :: 3.8
Requires-Dist: cssutils (>=1.0.2)
Requires-Dist: django-colorful (>=1.3)
Requires-Dist: libsass (>=0.14.5)
